<?xml version="1.0" encoding="UTF-8"?>
<QCARConfig xmlns:xsi="http://www.w3.org/2001/XMLSchema-instance" xsi:noNamespaceSchemaLocation="qcar_config.xsd">
  <Tracking>
    <ImageTarget name="MARK" size="6.000000 6.000000" />
    <ImageTarget name="MARK2" size="6.000000 6.000000" />
    <ImageTarget name="side2" size="2.000000 2.000000" />
    <ImageTarget name="side1" size="2.000000 2.000000" />
    <ImageTarget name="main" size="6.000000 6.000000" />
    <ImageTarget name="cardboard4" size="3.000000 3.000000" />
    <ImageTarget name="cardboard3" size="3.000000 3.000000" />
    <ImageTarget name="cardboard2" size="3.000000 3.000000" />
    <ImageTarget name="cardboard1" size="3.000000 3.000000" />
    <ImageTarget name="HackerGuide" size="4.000000 4.000000" />
  </Tracking>
</QCARConfig>
